bits/__init__.py
bits/jira/__init__.py
bits_jira-1.0.12.dist-info/METADATA
bits_jira-1.0.12.dist-info/WHEEL
bits_jira-1.0.12.dist-info/top_level.txt
bits_jira-1.0.12.dist-info/RECORD
