Metadata-Version: 2.1
Name: bits-jira
Version: 1.0.12
Summary: BITS JIRA
Home-page: UNKNOWN
Author: Lukas Karlsson
Author-email: karlsson@broadinstitute.org
License: Apache Software License
Platform: UNKNOWN
Requires-Dist: jira
